cyberpi/__init__.py
cyberpi-0.0.7.dist-info/METADATA
cyberpi-0.0.7.dist-info/WHEEL
cyberpi-0.0.7.dist-info/top_level.txt
cyberpi-0.0.7.dist-info/RECORD
