Metadata-Version: 1.0
Name: cyberpi
Version: 0.0.7
Summary: library for cyber-pi
Home-page: https://makeblock.com
Author: makeblock
Author-email: flashindream@gmail.com
License: UNKNOWN
Platform: UNKNOWN
